{
  "topbar.hours": "Lun–Vie 9:00–18:00",
  "brand.tag": "Centro multiservicios para ciudadanos e inmigrantes",
  "nav.services": "Servicios",
  "nav.how": "Cómo funciona",
  "nav.about": "Quiénes somos",
  "nav.languages": "Idiomas",
  "nav.contact": "Contacto",
  "nav.login": "Área privada",
  "nav.book": "Reservar",
  "hero.badge": "Todos los servicios en un solo centro",
  "hero.title": "Te atendemos en tu idioma",
  "hero.subtitle": "CAF, prestaciones, sindicatos, exámenes de lengua italiana, inmigración y asistencia jurídica. Reserva en línea, paga con seguridad y sigue tus trámites — en 5 idiomas.",
  "hero.ctaPrimary": "Reservar una cita",
  "hero.ctaSecondary": "Ver servicios",
  "profiles.title": "Encuentra lo que necesitas — ¿quién eres?",
  "profiles.worker": "Trabajador",
  "profiles.workerDesc": "Nóminas, declaración, contratos",
  "profiles.pensioner": "Pensionista",
  "profiles.pensionerDesc": "Pensiones, ISEE, ingresos",
  "profiles.migrant": "Ciudadano extranjero",
  "profiles.migrantDesc": "Permisos, ciudadanía, idioma",
  "profiles.business": "Empresa",
  "profiles.businessDesc": "Obligaciones, consultoría",
  "services.kicker": "Nuestros servicios",
  "services.title": "Seis áreas, un único punto de referencia",
  "services.subtitle": "Profesionales dedicados para cada necesidad, con atención en tu idioma.",
  "svc.cta": "Reservar",
  "svc.caf.t": "Asistencia fiscal (CAF)",
  "svc.caf.d": "Declaración de la renta, ISEE, impuestos, sucesiones, bonos y ayudas. Asistencia fiscal completa.",
  "svc.patr.t": "Servicios de previsión",
  "svc.patr.d": "Pensiones, invalidez, subsidios, desempleo, ayuda familiar, accidentes. Apoyo social gratuito.",
  "svc.sind.t": "Servicios sindicales",
  "svc.sind.d": "Protección del trabajador, conflictos, contratos, despidos, derechos y representación. Asesoría y asistencia.",
  "svc.lang.t": "Centro de exámenes de lengua italiana",
  "svc.lang.d": "Cursos y certificaciones CILS, CELI, PLIDA. Test A2 y B1 para permiso UE, preparación y certificados reconocidos.",
  "svc.immig.t": "Servicios de inmigración",
  "svc.immig.d": "Permiso de residencia, renovaciones, reagrupación familiar, ciudadanía, flujos, autorizaciones. Trámites completos.",
  "svc.legal.t": "Asistencia jurídica",
  "svc.legal.d": "Asesoría legal, contratos, derecho de familia, civil y administrativo. Abogados y representación.",
  "how.kicker": "Sencillo y rápido",
  "how.title": "Cómo funciona la reserva",
  "how.s1t": "Elige el servicio",
  "how.s1d": "Selecciona el área y el tipo de trámite, en tu idioma.",
  "how.s2t": "Reserva una cita",
  "how.s2d": "Elige sede, fecha y hora en la agenda en tiempo real.",
  "how.s3t": "Confirma y paga",
  "how.s3d": "Paga en línea con seguridad y recibe confirmación y recordatorios por correo y WhatsApp.",
  "why.kicker": "Por qué elegirnos",
  "why.title": "Un organismo en el que confiar",
  "why.desc": "Unimos competencias fiscales, sociales, jurídicas y lingüísticas para ofrecer un servicio único, multilingüe y centrado en las personas. Confidencialidad e integridad ante todo.",
  "why.li1": "Atención en italiano, árabe, inglés, francés y español",
  "why.li2": "Área privada para seguir el estado de tus trámites",
  "why.li3": "Tratamiento de datos seguro y conforme al RGPD",
  "why.stat1": "Trámites gestionados",
  "why.stat2": "Idiomas de atención",
  "why.stat3": "Áreas de servicio",
  "why.stat4": "Clientes satisfechos",
  "lang.title": "Te atendemos en tu idioma",
  "lang.subtitle": "Haz clic para cambiar de idioma en cualquier momento.",
  "cta.title": "¿Listo para reservar tu cita?",
  "cta.subtitle": "Elige el servicio, la hora y paga con seguridad. Todo en línea, en minutos.",
  "cta.book": "Abrir la agenda y reservar",
  "cta.whatsapp": "Escríbenos por WhatsApp",
  "cta.pay": "Pagos aceptados:",
  "footer.about": "Fiscal, Prestaciones, Trabajo, Inmigración, Examen de lengua italiana A2 y B1.",
  "footer.servicesT": "Servicios",
  "footer.contactT": "Contacto",
  "footer.legalT": "Información",
  "footer.privacy": "Privacidad y RGPD",
  "footer.terms": "Términos y condiciones",
  "footer.cookie": "Política de cookies",
  "footer.rights": "Todos los derechos reservados. CIF 01736510536",
  "booking.title": "Reservar una cita",
  "booking.subtitle": "Elige el servicio, la fecha y la hora. Recibirás confirmación por correo y WhatsApp.",
  "booking.step1": "Servicio",
  "booking.step2": "Fecha y hora",
  "booking.step3": "Tus datos",
  "booking.step4": "Confirmar",
  "booking.chooseService": "¿Qué servicio necesitas?",
  "booking.duration": "Duración",
  "booking.mins": "min",
  "booking.chooseDate": "Elige el día",
  "booking.chooseTime": "Elige la hora",
  "booking.morning": "Mañana",
  "booking.afternoon": "Tarde",
  "booking.noSlots": "No hay horarios disponibles este día. Elige otra fecha.",
  "booking.selectDateFirst": "Primero elige un día en el calendario.",
  "booking.yourDetails": "Introduce tus datos",
  "booking.firstName": "Nombre",
  "booking.lastName": "Apellidos",
  "booking.email": "Correo electrónico",
  "booking.phone": "Teléfono",
  "booking.notes": "Notas (opcional)",
  "booking.notesPh": "Ej. tipo de trámite, documentos, idioma preferido…",
  "booking.summary": "Resumen",
  "booking.lblService": "Servicio",
  "booking.lblWhen": "Fecha y hora",
  "booking.lblName": "Nombre",
  "booking.lblLocation": "Sede",
  "booking.back": "Atrás",
  "booking.next": "Siguiente",
  "booking.confirm": "Confirmar la cita",
  "booking.confirmedTitle": "¡Cita confirmada!",
  "booking.confirmedMsg": "Te hemos enviado los detalles por correo. ¡Te esperamos!",
  "booking.newBooking": "Nueva cita",
  "booking.required": "Campo obligatorio",
  "booking.invalidEmail": "Correo no válido",
  "booking.submitting": "Enviando…",
  "booking.error": "Se ha producido un error. Inténtalo de nuevo o contáctanos.",
  "booking.whatsappConfirm": "Enviar confirmación por WhatsApp",
  "booking.ref": "Referencia",
  "svcpage.allServices": "Todos los servicios",
  "svcpage.whatWeDo": "Qué hacemos",
  "svcpage.docs": "Documentos necesarios",
  "svcpage.note": "Bueno saberlo",
  "svcpage.bookThis": "Reservar este servicio",
  "svcpage.help": "¿Necesitas ayuda?",
  "svcpage.langNote": "La información detallada está en italiano. Te atendemos en tu idioma en nuestra oficina y por teléfono.",
  "legal.updated": "Última actualización",
  "legal.note": "Documento en italiano. Para aclaraciones en tu idioma, contáctanos.",
  "team.kicker": "Nuestro equipo",
  "team.title": "Las personas a tu servicio",
  "team.subtitle": "Profesionales cualificados, listos para atenderte en tu idioma.",
  "team.langs": "Idiomas",
  "team.pageIntro": "USI – CUNEOServizi es el punto de referencia en Cuneo para los servicios a ciudadanos e inmigrantes. Nuestro equipo une competencias sindicales, jurídicas, fiscales y de inmigración para ofrecerte una asistencia completa en tu idioma.",
  "team.bookCta": "Reservar una cita"
}
